README.md
setup.py
vista_api_client/__init__.py
vista_api_client/vista.py
vista_api_client.egg-info/PKG-INFO
vista_api_client.egg-info/SOURCES.txt
vista_api_client.egg-info/dependency_links.txt
vista_api_client.egg-info/requires.txt
vista_api_client.egg-info/top_level.txt
vista_api_client/api_resources/__init__.py
vista_api_client/api_resources/admin.py
vista_api_client/api_resources/api_resource.py
vista_api_client/api_resources/grants.py
vista_api_client/api_resources/resource_types.py
vista_api_client/api_resources/roles.py
vista_api_client/api_resources/users.py
vista_api_client/api_resources/usersets.py
vista_api_client/config/__init__.py
vista_api_client/config/config.py