Metadata-Version: 2.1
Name: vista-api-client
Version: 0.4.1
Summary: Client for the Vista API
Home-page: https://github.com/siddhantdange/vista-clients
Author: Sid Dange
Author-email: sid@govista.io
License: MIT
Download-URL: https://github.com/siddhantdange/vista-clients/archive/v_01.tar.gz
Keywords: vista,authz,permissions,vista-authz,vistaio
Platform: UNKNOWN
Classifier: Development Status :: 5 - Production/Stable
Classifier: Intended Audience :: Developers
Classifier: Topic :: Software Development :: Build Tools
Classifier: License :: OSI Approved :: MIT License
Classifier: Programming Language :: Python :: 3
Classifier: Programming Language :: Python :: 3.4
Classifier: Programming Language :: Python :: 3.5
Classifier: Programming Language :: Python :: 3.6
